{
  "member_id": "MBR-000249",
  "step_number": 4,
  "step": 4,
  "step_name": "cost",
  "detail": {
    "outcome": "costed",
    "outcome_value": "Total cost: $109,441.70, PMPM: $9,120.14 (12 member-months)",
    "logic_trace": [
      "Total cost: $109,441.70, PMPM: $9,120.14 (12 member-months)"
    ],
    "flags": [],
    "intermediate_values": [
      {
        "label": "total_cost",
        "value": 109441.7
      },
      {
        "label": "member_months",
        "value": 12
      },
      {
        "label": "member_pmpm",
        "value": 9120.14
      }
    ]
  },
  "data_references": [
    {
      "file": "claims_professional.csv",
      "row_index": 12549,
      "columns": {
        "claim_id": null,
        "member_id": null,
        "allowed_amount": null,
        "service_date": null
      },
      "description": "77 professional claims, $26,173.09"
    },
    {
      "file": "claims_professional.csv",
      "row_index": 12550,
      "columns": {
        "claim_id": null,
        "member_id": null,
        "allowed_amount": null,
        "service_date": null
      },
      "description": "77 professional claims, $26,173.09"
    },
    {
      "file": "claims_professional.csv",
      "row_index": 12551,
      "columns": {
        "claim_id": null,
        "member_id": null,
        "allowed_amount": null,
        "service_date": null
      },
      "description": "77 professional claims, $26,173.09"
    },
    {
      "file": "claims_professional.csv",
      "row_index": 12552,
      "columns": {
        "claim_id": null,
        "member_id": null,
        "allowed_amount": null,
        "service_date": null
      },
      "description": "77 professional claims, $26,173.09"
    },
    {
      "file": "claims_professional.csv",
      "row_index": 12553,
      "columns": {
        "claim_id": null,
        "member_id": null,
        "allowed_amount": null,
        "service_date": null
      },
      "description": "77 professional claims, $26,173.09"
    },
    {
      "file": "claims_professional.csv",
      "row_index": 12554,
      "columns": {
        "claim_id": null,
        "member_id": null,
        "allowed_amount": null,
        "service_date": null
      },
      "description": "77 professional claims, $26,173.09"
    },
    {
      "file": "claims_professional.csv",
      "row_index": 12555,
      "columns": {
        "claim_id": null,
        "member_id": null,
        "allowed_amount": null,
        "service_date": null
      },
      "description": "77 professional claims, $26,173.09"
    },
    {
      "file": "claims_professional.csv",
      "row_index": 12556,
      "columns": {
        "claim_id": null,
        "member_id": null,
        "allowed_amount": null,
        "service_date": null
      },
      "description": "77 professional claims, $26,173.09"
    },
    {
      "file": "claims_professional.csv",
      "row_index": 12557,
      "columns": {
        "claim_id": null,
        "member_id": null,
        "allowed_amount": null,
        "service_date": null
      },
      "description": "77 professional claims, $26,173.09"
    },
    {
      "file": "claims_professional.csv",
      "row_index": 12558,
      "columns": {
        "claim_id": null,
        "member_id": null,
        "allowed_amount": null,
        "service_date": null
      },
      "description": "77 professional claims, $26,173.09"
    },
    {
      "file": "claims_facility.csv",
      "row_index": 1767,
      "columns": {
        "claim_id": null,
        "member_id": null,
        "allowed_amount": null,
        "service_date": null
      },
      "description": "10 facility claims, $83,268.61"
    },
    {
      "file": "claims_facility.csv",
      "row_index": 1768,
      "columns": {
        "claim_id": null,
        "member_id": null,
        "allowed_amount": null,
        "service_date": null
      },
      "description": "10 facility claims, $83,268.61"
    },
    {
      "file": "claims_facility.csv",
      "row_index": 1769,
      "columns": {
        "claim_id": null,
        "member_id": null,
        "allowed_amount": null,
        "service_date": null
      },
      "description": "10 facility claims, $83,268.61"
    },
    {
      "file": "claims_facility.csv",
      "row_index": 1770,
      "columns": {
        "claim_id": null,
        "member_id": null,
        "allowed_amount": null,
        "service_date": null
      },
      "description": "10 facility claims, $83,268.61"
    },
    {
      "file": "claims_facility.csv",
      "row_index": 1771,
      "columns": {
        "claim_id": null,
        "member_id": null,
        "allowed_amount": null,
        "service_date": null
      },
      "description": "10 facility claims, $83,268.61"
    },
    {
      "file": "claims_facility.csv",
      "row_index": 1772,
      "columns": {
        "claim_id": null,
        "member_id": null,
        "allowed_amount": null,
        "service_date": null
      },
      "description": "10 facility claims, $83,268.61"
    },
    {
      "file": "claims_facility.csv",
      "row_index": 1773,
      "columns": {
        "claim_id": null,
        "member_id": null,
        "allowed_amount": null,
        "service_date": null
      },
      "description": "10 facility claims, $83,268.61"
    },
    {
      "file": "claims_facility.csv",
      "row_index": 1774,
      "columns": {
        "claim_id": null,
        "member_id": null,
        "allowed_amount": null,
        "service_date": null
      },
      "description": "10 facility claims, $83,268.61"
    },
    {
      "file": "claims_facility.csv",
      "row_index": 1775,
      "columns": {
        "claim_id": null,
        "member_id": null,
        "allowed_amount": null,
        "service_date": null
      },
      "description": "10 facility claims, $83,268.61"
    },
    {
      "file": "claims_facility.csv",
      "row_index": 1776,
      "columns": {
        "claim_id": null,
        "member_id": null,
        "allowed_amount": null,
        "service_date": null
      },
      "description": "10 facility claims, $83,268.61"
    }
  ],
  "contract_clauses": [
    {
      "id": "COST-1.0",
      "text": "Total cost of care shall be calculated as the sum of all Parts A and B allowed charges for attributed beneficiaries during the performance year, divided by the number of attributed beneficiary-months, expressed as a per-member-per-month (PMPM) amount. Claims with service dates within the performance year that are adjudicated within 3 months of the performance year end shall be included.",
      "section": "Calculate total cost using allowed amount as the cost basis. Excluding pharmacy claims. Claims run-out window: 3 months after performance year end.",
      "title": "COST-1.0",
      "parameters": {
        "cost_basis": "allowed_amount",
        "include_pharmacy": false,
        "runout_months": 3
      }
    }
  ],
  "code_references": [
    {
      "module": "step_4_cost",
      "function": "calculate_cost",
      "lines": "51-240",
      "start_line": 51,
      "end_line": 240,
      "logic_summary": "Sum allowed amounts for attributed members' paid claims during the performance year. Calculate member-months from eligibility. Apply claims maturity adjustment for incomplete months. Compute raw and adjusted PMPM with confidence bands."
    }
  ]
}
