{
  "item_type": "hcc",
  "item_id": "HCC 18",
  "detail": {
    "condition_name": "Diabetes with Chronic Complications",
    "icd10_code": "E11.21",
    "hcc_category": "HCC 18",
    "estimated_raf_impact": 0.302,
    "evidence_source": "Prior year claims",
    "last_captured_date": "2024-08-15",
    "provenance": {
      "step": "quality",
      "step_number": 3,
      "member_id": "MBR-000146"
    }
  },
  "provenance": {
    "step": "quality",
    "step_number": 3,
    "member_id": "MBR-000146"
  },
  "clinical_question": "Why is Diabetes with Chronic Complications flagged for documentation?"
}
